[
  {
    "id": 32369,
    "title": "海牙热身赛1-2告负，张玉宁首发出战55分钟",
    "summary": "",
    "publishTime": 1531187862000,
    "isHeadline": 0,
    "headlineWeight": 1,
    "category": "zq",
    "format": 1,
    "tag": "荷甲 ",
    "imageList": [
      "https://qmcms.oss-cn-beijing.aliyuncs.com/sns/image/201807/16481ebabbb.jpg"
    ],
    "lotNo": "zq_zgzq",
    "_id": 32369,
    "tagColor": "#f2384b",
    "weight": 0,
    "videoId": 0,
    "visitCount": 38
  },
  {
    "id": 32356,
    "title": "镜报：埃弗顿渴望签下水晶宫边锋扎哈",
    "summary": "",
    "publishTime": 1531185723000,
    "isHeadline": 0,
    "headlineWeight": 1,
    "category": "zq",
    "format": 1,
    "imageList": [
      "https://qmcms.oss-cn-beijing.aliyuncs.com/sns/image/201807/16481eba68b.jpg"
    ],
    "lotNo": "zq_gjzq",
    "_id": 32356,
    "tagColor": "#f2384b",
    "weight": 0,
    "videoId": 0,
    "visitCount": 2
  },
  {
    "id": 32357,
    "title": "曼联续约两名小将迪恩利和威兰",
    "summary": "",
    "publishTime": 1531185507000,
    "isHeadline": 0,
    "headlineWeight": 1,
    "category": "zq",
    "format": 1,
    "imageList": [
      "https://qmcms.oss-cn-beijing.aliyuncs.com/sns/image/201807/16481eba7b2.jpg"
    ],
    "lotNo": "zq_gjzq",
    "_id": 32357,
    "tagColor": "#f2384b",
    "weight": 0,
    "videoId": 0,
    "visitCount": 6
  },
  {
    "id": 32358,
    "title": "为提前转会巴萨，阿图尔自讨腰包补齐差价",
    "summary": "",
    "publishTime": 1531182071000,
    "isHeadline": 0,
    "headlineWeight": 1,
    "category": "zq",
    "format": 1,
    "imageList": [
      "https://qmcms.oss-cn-beijing.aliyuncs.com/sns/image/201807/16481b4b74b.png"
    ],
    "lotNo": "zq_gjzq",
    "_id": 32358,
    "tagColor": "#f2384b",
    "weight": 0,
    "videoId": 0,
    "visitCount": 16,
    "tag": "西甲"
  },
  {
    "id": 32359,
    "title": "经纪人：阿森西奥不会离开皇马，下赛季对他很重要",
    "summary": "",
    "publishTime": 1531179001000,
    "isHeadline": 0,
    "headlineWeight": 1,
    "category": "zq",
    "format": 1,
    "imageList": [
      "https://qmcms.oss-cn-beijing.aliyuncs.com/sns/image/201807/164817dc6bd.png"
    ],
    "lotNo": "zq_gjzq",
    "_id": 32359,
    "tagColor": "#f2384b",
    "weight": 0,
    "videoId": 0,
    "visitCount": 8
  },
  {
    "id": 32374,
    "title": "米拉贝利：苏索想留下，他肯定不会去国米",
    "summary": "",
    "publishTime": 1531178311000,
    "isHeadline": 1,
    "headlineWeight": 1,
    "category": "zq",
    "format": 1,
    "imageList": [
      "https://qmcms.oss-cn-beijing.aliyuncs.com/sns/image/201807/164817dc7ca.jpg"
    ],
    "lotNo": "zq_ozss",
    "_id": 32374,
    "tagColor": "#f2384b",
    "weight": 0,
    "videoId": 0,
    "visitCount": 10,
    "tag": "意甲"
  },
  {
    "id": 32361,
    "title": "布冯：若C罗真加盟尤文，我会为此感到开心",
    "summary": "",
    "publishTime": 1531176338000,
    "isHeadline": 0,
    "headlineWeight": 1,
    "category": "zq",
    "format": 1,
    "imageList": [
      "https://qmcms.oss-cn-beijing.aliyuncs.com/sns/image/201807/1648146ddcf.jpg"
    ],
    "lotNo": "zq_gjzq",
    "_id": 32361,
    "tagColor": "#f2384b",
    "weight": 0,
    "videoId": 0,
    "visitCount": 8
  },
  {
    "id": 32362,
    "title": "官方：拜仁慕尼黑签下美国年轻中卫",
    "summary": "",
    "publishTime": 1531176092000,
    "isHeadline": 0,
    "headlineWeight": 1,
    "category": "zq",
    "format": 1,
    "imageList": [
      "https://qmcms.oss-cn-beijing.aliyuncs.com/sns/image/201807/1648146de6b.jpg"
    ],
    "lotNo": "zq_gjzq",
    "_id": 32362,
    "tagColor": "#f2384b",
    "weight": 0,
    "videoId": 0,
    "visitCount": 7
  },
  {
    "id": 32363,
    "title": "官方：汉堡前锋伍德租借加盟汉诺威",
    "summary": "",
    "publishTime": 1531175720000,
    "isHeadline": 0,
    "headlineWeight": 1,
    "category": "zq",
    "format": 1,
    "imageList": [
      "https://qmcms.oss-cn-beijing.aliyuncs.com/sns/image/201807/1648146df69.jpg"
    ],
    "lotNo": "zq_gjzq",
    "_id": 32363,
    "tagColor": "#f2384b",
    "weight": 0,
    "videoId": 0,
    "visitCount": 4
  },
  {
    "id": 32364,
    "title": "意大利天空体育：未来48小时C罗转会将出现重大进展",
    "summary": "",
    "publishTime": 1531171870000,
    "isHeadline": 1,
    "headlineWeight": 1,
    "category": "zq",
    "format": 1,
    "imageList": [
      "https://qmcms.oss-cn-beijing.aliyuncs.com/sns/image/201807/164810fe720.jpg"
    ],
    "lotNo": "zq_gjzq",
    "_id": 32364,
    "tagColor": "#12ae5b",
    "weight": 0,
    "videoId": 0,
    "visitCount": 24,
    "tag": "西甲"
  },
  {
    "id": 32354,
    "title": "曝权健3年合同正式报价巴神 年薪1100万欧被拒绝",
    "summary": "",
    "publishTime": 1531170360000,
    "isHeadline": 0,
    "headlineWeight": 1,
    "category": "zq",
    "format": 1,
    "imageList": [
      "https://qmcms.oss-cn-beijing.aliyuncs.com/sns/image/201807/164810fe931.jpg"
    ],
    "lotNo": "zq_zgzq",
    "_id": 32354,
    "tagColor": "#f2384b",
    "weight": 0,
    "videoId": 0,
    "visitCount": 10,
    "tag": "中超"
  },
  {
    "id": 32365,
    "title": "尴尬!惨淡世界杯后无人报价 莱万又想继续留拜仁",
    "summary": "",
    "publishTime": 1531168968000,
    "isHeadline": 0,
    "headlineWeight": 1,
    "category": "zq",
    "format": 1,
    "imageList": [
      "https://qmcms.oss-cn-beijing.aliyuncs.com/sns/image/201807/16480d91574.jpg"
    ],
    "lotNo": "zq_gjzq",
    "_id": 32365,
    "tagColor": "#f2384b",
    "weight": 0,
    "videoId": 0,
    "visitCount": 12
  },
  {
    "id": 32366,
    "title": "官方：阿图尔将立即加盟巴萨，转会费最高4000万欧",
    "summary": "",
    "publishTime": 1531167589000,
    "isHeadline": 0,
    "headlineWeight": 1,
    "category": "zq",
    "format": 1,
    "imageList": [
      "https://qmcms.oss-cn-beijing.aliyuncs.com/sns/image/201807/16480d8f9a3.jpg"
    ],
    "lotNo": "zq_gjzq",
    "_id": 32366,
    "tagColor": "#f2384b",
    "weight": 0,
    "videoId": 0,
    "visitCount": 7
  },
  {
    "id": 32367,
    "title": "阿森纳17年太子正式加盟西汉姆 签3年周薪10万镑",
    "summary": "",
    "publishTime": 1531147409000,
    "isHeadline": 1,
    "headlineWeight": 1,
    "category": "zq",
    "format": 1,
    "imageList": [
      "https://qmcms.oss-cn-beijing.aliyuncs.com/sns/image/201807/1647f8f88b3.jpg"
    ],
    "lotNo": "zq_gjzq",
    "_id": 32367,
    "tagColor": "#12ae5b",
    "weight": 0,
    "videoId": 0,
    "visitCount": 20,
    "tag": "英超"
  },
  {
    "id": 32368,
    "title": "官方：卡迪夫城与球队中场贡纳松续约1年",
    "summary": "",
    "publishTime": 1531146502000,
    "isHeadline": 0,
    "headlineWeight": 1,
    "category": "zq",
    "format": 1,
    "imageList": [
      "https://qmcms.oss-cn-beijing.aliyuncs.com/sns/image/201807/1647f8f679b.jpg"
    ],
    "lotNo": "zq_gjzq",
    "_id": 32368,
    "tagColor": "#f2384b",
    "weight": 0,
    "videoId": 0,
    "visitCount": 3
  },
  {
    "id": 32375,
    "title": "曝国米将先租后买留下巴萨大将 总支出超3000万欧",
    "summary": "",
    "publishTime": 1531145400000,
    "isHeadline": 1,
    "headlineWeight": 1,
    "category": "zq",
    "format": 1,
    "imageList": [
      "https://qmcms.oss-cn-beijing.aliyuncs.com/sns/image/201807/1647f8f705e.jpg"
    ],
    "lotNo": "zq_gjzq",
    "_id": 32375,
    "tagColor": "#12ae5b",
    "weight": 0,
    "videoId": 0,
    "visitCount": 5,
    "tag": "意甲"
  },
  {
    "id": 32376,
    "title": "多方消息证实切尔西正试图截胡若日尼奥",
    "summary": "",
    "publishTime": 1531138742000,
    "isHeadline": 0,
    "headlineWeight": 1,
    "category": "zq",
    "format": 1,
    "imageList": [
      "https://qmcms.oss-cn-beijing.aliyuncs.com/sns/image/201807/1647f218bc2.jpg"
    ],
    "lotNo": "zq_gjzq",
    "_id": 32376,
    "tagColor": "#f2384b",
    "weight": 0,
    "videoId": 0,
    "visitCount": 4
  },
  {
    "id": 32378,
    "title": "官方：朗尼克新赛季将担任RB莱比锡主教练",
    "summary": "",
    "publishTime": 1531134375000,
    "isHeadline": 0,
    "headlineWeight": 1,
    "category": "zq",
    "format": 1,
    "imageList": [
      "https://qmcms.oss-cn-beijing.aliyuncs.com/sns/image/201807/1647eeaa07f.png"
    ],
    "lotNo": "zq_gjzq",
    "_id": 32378,
    "tagColor": "#f2384b",
    "weight": 0,
    "videoId": 0,
    "visitCount": 3
  },
  {
    "id": 32379,
    "title": "官方：阿森纳新援莱诺将在新赛季身披19号球衣",
    "summary": "",
    "publishTime": 1531131061000,
    "isHeadline": 0,
    "headlineWeight": 1,
    "category": "zq",
    "format": 1,
    "imageList": [
      "https://qmcms.oss-cn-beijing.aliyuncs.com/sns/image/201807/1647eb3ad98.jpg"
    ],
    "lotNo": "zq_ozss",
    "_id": 32379,
    "tagColor": "#f2384b",
    "weight": 0,
    "videoId": 0,
    "visitCount": 4,
    "tag": "英超"
  },
  {
    "id": 32322,
    "title": "继续握手？比利时首相、法国总统均将现身世界杯半决赛",
    "summary": "",
    "publishTime": 1531101160000,
    "isHeadline": 1,
    "headlineWeight": 1,
    "category": "zq",
    "format": 1,
    "imageList": [
      "https://qmcms.oss-cn-beijing.aliyuncs.com/sns/image/201807/1647cc54864.jpg"
    ],
    "lotNo": "zq_gjzq",
    "_id": 32322,
    "tagColor": "#f2384b",
    "weight": 0,
    "videoId": 0,
    "visitCount": 606,
    "tag": "世界杯"
  },
  {
    "id": 32323,
    "title": "佩特莱斯库：贵州更应赢球，接下来全力迎战恒大",
    "summary": "",
    "publishTime": 1531098644000,
    "isHeadline": 0,
    "headlineWeight": 1,
    "category": "zq",
    "format": 1,
    "imageList": [
      "https://qmcms.oss-cn-beijing.aliyuncs.com/sns/image/201807/1647cc5515a.jpg"
    ],
    "lotNo": "zq_zgzq",
    "_id": 32323,
    "tagColor": "#f2384b",
    "weight": 0,
    "videoId": 0,
    "visitCount": 46,
    "tag": "中超"
  },
  {
    "id": 32324,
    "title": "巴萨官方为保利尼奥送上祝福，确认租借合同含买断条款",
    "summary": "",
    "publishTime": 1531097555000,
    "isHeadline": 1,
    "headlineWeight": 1,
    "category": "zq",
    "format": 1,
    "imageList": [
      "https://qmcms.oss-cn-beijing.aliyuncs.com/sns/image/201807/1647c8e575d.jpg"
    ],
    "lotNo": "zq_gjzq",
    "_id": 32324,
    "tagColor": "#f2384b",
    "weight": 0,
    "videoId": 0,
    "visitCount": 113,
    "tag": "西甲"
  },
  {
    "id": 32303,
    "title": "卡瓦尼可能回意甲，尤文那不勒斯或是下家",
    "summary": "",
    "publishTime": 1531093771000,
    "isHeadline": 0,
    "headlineWeight": 1,
    "category": "zq",
    "format": 1,
    "imageList": [
      "https://qmcms.oss-cn-beijing.aliyuncs.com/sns/image/201807/1647c576b9d.jpg"
    ],
    "lotNo": "zq_gjzq",
    "_id": 32303,
    "tagColor": "#f2384b",
    "weight": 0,
    "videoId": 0,
    "visitCount": 68,
    "tag": "意甲"
  },
  {
    "id": 32304,
    "title": "多名主力球员未回归，瓦格纳成拜仁训练时大佬",
    "summary": "",
    "publishTime": 1531093383000,
    "isHeadline": 0,
    "headlineWeight": 1,
    "category": "zq",
    "format": 1,
    "imageList": [
      "https://qmcms.oss-cn-beijing.aliyuncs.com/sns/image/201807/1647c576c68.jpg"
    ],
    "lotNo": "zq_gjzq",
    "_id": 32304,
    "tagColor": "#f2384b",
    "weight": 0,
    "videoId": 0,
    "visitCount": 88,
    "tag": "德甲 "
  },
  {
    "id": 32318,
    "title": "传拉齐奥有意阿森纳前锋乔尔-坎贝尔",
    "summary": "",
    "publishTime": 1531092815000,
    "isHeadline": 0,
    "headlineWeight": 1,
    "category": "zq",
    "format": 1,
    "imageList": [
      "https://qmcms.oss-cn-beijing.aliyuncs.com/sns/image/201807/1647c576ecc.jpg"
    ],
    "lotNo": "zq_gjzq",
    "_id": 32318,
    "tagColor": "#f2384b",
    "weight": 0,
    "videoId": 0,
    "visitCount": 14
  },
  {
    "id": 32311,
    "title": "西媒炮轰巴萨卖保利尼奥:皇马收割欧冠 你们却眼瞎",
    "summary": "",
    "publishTime": 1531088376000,
    "isHeadline": 0,
    "headlineWeight": 1,
    "category": "zq",
    "format": 1,
    "imageList": [
      "https://qmcms.oss-cn-beijing.aliyuncs.com/sns/image/201807/1647c209a91.jpg"
    ],
    "lotNo": "zq_gjzq",
    "_id": 32311,
    "tagColor": "#f2384b",
    "weight": 0,
    "videoId": 0,
    "visitCount": 87,
    "tag": "西甲"
  },
  {
    "id": 32312,
    "title": "重磅!西班牙新帅人选被曝光:前巴萨主帅恩里克接任",
    "summary": "",
    "publishTime": 1531087930000,
    "isHeadline": 0,
    "headlineWeight": 1,
    "category": "zq",
    "format": 1,
    "imageList": [
      "https://qmcms.oss-cn-beijing.aliyuncs.com/sns/image/201807/1647c209b35.jpg"
    ],
    "lotNo": "zq_gjzq",
    "_id": 32312,
    "tagColor": "#f2384b",
    "weight": 0,
    "videoId": 0,
    "visitCount": 17
  },
  {
    "id": 32319,
    "title": "曝热刺也看上巴萨巨人!但波帅不会满足他上场时间",
    "summary": "",
    "publishTime": 1531086885000,
    "isHeadline": 0,
    "headlineWeight": 1,
    "category": "zq",
    "format": 1,
    "imageList": [
      "https://qmcms.oss-cn-beijing.aliyuncs.com/sns/image/201807/1647c20a46f.png"
    ],
    "lotNo": "zq_gjzq",
    "_id": 32319,
    "tagColor": "#f2384b",
    "weight": 0,
    "videoId": 0,
    "visitCount": 55,
    "tag": "英超"
  },
  {
    "id": 32320,
    "title": "梅萨经纪人：先去热那亚再去国米？我喜欢这个方案",
    "summary": "",
    "publishTime": 1531084298000,
    "isHeadline": 0,
    "headlineWeight": 1,
    "category": "zq",
    "format": 1,
    "imageList": [
      "https://qmcms.oss-cn-beijing.aliyuncs.com/sns/image/201807/1647be98da1.jpg"
    ],
    "lotNo": "zq_gjzq",
    "_id": 32320,
    "tagColor": "#f2384b",
    "weight": 0,
    "videoId": 0,
    "visitCount": 16,
    "tag": "意甲"
  },
  {
    "id": 32302,
    "title": "官方：保利尼奥租借加盟恒大一年",
    "summary": "",
    "publishTime": 1531068638000,
    "isHeadline": 1,
    "headlineWeight": 1,
    "category": "zq",
    "format": 1,
    "imageList": [
      "https://qmcms.oss-cn-beijing.aliyuncs.com/sns/image/201807/1647ad6e50d.jpg"
    ],
    "lotNo": "zq_zgzq",
    "_id": 32302,
    "tagColor": "#f2384b",
    "weight": 0,
    "videoId": 0,
    "visitCount": 97,
    "tag": "中超"
  },
  {
    "id": 32314,
    "title": "巴洛特利抵达马赛接受体检，即将签下两年合约",
    "summary": "",
    "publishTime": 1531060490000,
    "isHeadline": 0,
    "headlineWeight": 1,
    "category": "zq",
    "format": 1,
    "imageList": [
      "https://qmcms.oss-cn-beijing.aliyuncs.com/sns/image/201807/1647a690a5c.jpg"
    ],
    "lotNo": "zq_gjzq",
    "_id": 32314,
    "tagColor": "#f2384b",
    "weight": 0,
    "videoId": 0,
    "visitCount": 23,
    "tag": "法甲"
  },
  {
    "id": 32315,
    "title": "马卡报：皇马夏窗将会瞄准哈里-凯恩",
    "summary": "",
    "publishTime": 1531058357000,
    "isHeadline": 0,
    "headlineWeight": 1,
    "category": "zq",
    "format": 1,
    "imageList": [
      "https://qmcms.oss-cn-beijing.aliyuncs.com/sns/image/201807/1647a690fbb.jpg"
    ],
    "lotNo": "zq_gjzq",
    "_id": 32315,
    "tagColor": "#f2384b",
    "weight": 0,
    "videoId": 0,
    "visitCount": 24,
    "tag": "西甲"
  },
  {
    "id": 32316,
    "title": "邮报：马赫雷斯将在未来48小时内接受曼城体检",
    "summary": "",
    "publishTime": 1531057013000,
    "isHeadline": 0,
    "headlineWeight": 1,
    "category": "zq",
    "format": 1,
    "imageList": [
      "https://qmcms.oss-cn-beijing.aliyuncs.com/sns/image/201807/1647a321ace.jpg"
    ],
    "lotNo": "zq_gjzq",
    "_id": 32316,
    "tagColor": "#f2384b",
    "weight": 0,
    "videoId": 0,
    "visitCount": 26,
    "tag": "英超"
  },
  {
    "id": 32317,
    "title": "世界足球先生10人候选名单将于本月23日公布",
    "summary": "",
    "publishTime": 1531056997000,
    "isHeadline": 0,
    "headlineWeight": 1,
    "category": "zq",
    "format": 1,
    "imageList": [
      "https://qmcms.oss-cn-beijing.aliyuncs.com/sns/image/201807/1647a321b38.jpg"
    ],
    "lotNo": "zq_gjzq",
    "_id": 32317,
    "tagColor": "#f2384b",
    "weight": 0,
    "videoId": 0,
    "visitCount": 109,
    "tag": "国际足球其他"
  },
  {
    "id": 32297,
    "title": "重返球场！皇马旧将德伦特复出签约荷乙球队",
    "summary": "",
    "publishTime": 1531048639000,
    "isHeadline": 0,
    "headlineWeight": 1,
    "category": "zq",
    "format": 1,
    "imageList": [
      "https://qmcms.oss-cn-beijing.aliyuncs.com/sns/image/201807/16479c440ad.jpg"
    ],
    "lotNo": "zq_gjzq",
    "_id": 32297,
    "tagColor": "#f2384b",
    "weight": 0,
    "videoId": 0,
    "visitCount": 31
  },
  {
    "id": 32290,
    "title": "世体：巴萨急需补强中场，优先目标威廉和拉比奥",
    "summary": "",
    "publishTime": 1531028666000,
    "isHeadline": 0,
    "headlineWeight": 1,
    "category": "zq",
    "format": 1,
    "imageList": [
      "https://qmcms.oss-cn-beijing.aliyuncs.com/sns/image/201807/164787aa42d.jpg"
    ],
    "lotNo": "zq_gjzq",
    "_id": 32290,
    "tagColor": "#f2384b",
    "weight": 0,
    "videoId": 0,
    "visitCount": 60
  },
  {
    "id": 32291,
    "title": "胜败皆是英雄！被淘汰出局后，俄罗斯主帅仍收到普京致电",
    "summary": "",
    "publishTime": 1531028616000,
    "isHeadline": 0,
    "headlineWeight": 1,
    "category": "zq",
    "format": 1,
    "imageList": [
      "https://qmcms.oss-cn-beijing.aliyuncs.com/sns/image/201807/164787aa59e.jpg"
    ],
    "lotNo": "zq_gjzq",
    "_id": 32291,
    "tagColor": "#f2384b",
    "weight": 0,
    "videoId": 0,
    "visitCount": 78
  },
  {
    "id": 32292,
    "title": "久巴：我们向俄罗斯证明我们的足球还活着，这令我们很骄傲",
    "summary": "",
    "publishTime": 1531023910000,
    "isHeadline": 0,
    "headlineWeight": 1,
    "category": "zq",
    "format": 1,
    "imageList": [
      "https://qmcms.oss-cn-beijing.aliyuncs.com/sns/image/201807/1647843b663.jpg"
    ],
    "lotNo": "zq_gjzq",
    "_id": 32292,
    "tagColor": "#f2384b",
    "weight": 0,
    "videoId": 0,
    "visitCount": 32
  },
  {
    "id": 32293,
    "title": "扎哈维4000万美金赴上港?富力高层:没收到报价",
    "summary": "",
    "publishTime": 1531023060000,
    "isHeadline": 0,
    "headlineWeight": 1,
    "category": "zq",
    "format": 1,
    "imageList": [
      "https://qmcms.oss-cn-beijing.aliyuncs.com/sns/image/201807/1647843b536.jpg"
    ],
    "lotNo": "zq_zgzq",
    "_id": 32293,
    "tagColor": "#f2384b",
    "weight": 0,
    "videoId": 0,
    "visitCount": 34
  },
  {
    "id": 32283,
    "title": "官方：切尔西三门爱德华多租借加盟维特斯",
    "summary": "",
    "publishTime": 1531020967000,
    "isHeadline": 0,
    "headlineWeight": 1,
    "category": "zq",
    "format": 1,
    "imageList": [
      "https://qmcms.oss-cn-beijing.aliyuncs.com/sns/image/201807/164780ccaf4.jpg"
    ],
    "lotNo": "zq_gjzq",
    "_id": 32283,
    "tagColor": "#f2384b",
    "weight": 0,
    "videoId": 0,
    "visitCount": 46,
    "tag": "英超"
  },
  {
    "id": 32269,
    "title": "莫德里奇：我不希望C罗离开，我认为他会留在皇马",
    "summary": "",
    "publishTime": 1531010158000,
    "isHeadline": 0,
    "headlineWeight": 1,
    "category": "zq",
    "format": 1,
    "imageList": [
      "https://qmcms.oss-cn-beijing.aliyuncs.com/sns/image/201807/1647767fbbc.png"
    ],
    "lotNo": "zq_gjzq",
    "_id": 32269,
    "tagColor": "#f2384b",
    "weight": 0,
    "videoId": 0,
    "visitCount": 83,
    "tag": "西甲"
  },
  {
    "id": 32270,
    "title": "多特新赛季备战正式开始，球员进行体检",
    "summary": "",
    "publishTime": 1531007931000,
    "isHeadline": 0,
    "headlineWeight": 1,
    "category": "zq",
    "format": 1,
    "imageList": [
      "https://qmcms.oss-cn-beijing.aliyuncs.com/sns/image/201807/164776804f2.jpg"
    ],
    "lotNo": "zq_gjzq",
    "_id": 32270,
    "tagColor": "#f2384b",
    "weight": 0,
    "videoId": 0,
    "visitCount": 47,
    "tag": "德甲 "
  },
  {
    "id": 32271,
    "title": "官方：美因茨签下法国年轻中卫",
    "summary": "",
    "publishTime": 1531007531000,
    "isHeadline": 0,
    "headlineWeight": 1,
    "category": "zq",
    "format": 1,
    "imageList": [
      "https://qmcms.oss-cn-beijing.aliyuncs.com/sns/image/201807/16477310dde.jpg"
    ],
    "lotNo": "zq_gjzq",
    "_id": 32271,
    "tagColor": "#f2384b",
    "weight": 0,
    "videoId": 0,
    "visitCount": 25
  },
  {
    "id": 32273,
    "title": "塞尔塔体育总监：罗伯特卡决定离队",
    "summary": "",
    "publishTime": 1530997011000,
    "isHeadline": 0,
    "headlineWeight": 1,
    "category": "zq",
    "format": 1,
    "imageList": [
      "https://qmcms.oss-cn-beijing.aliyuncs.com/sns/image/201807/164768c415a.jpg"
    ],
    "lotNo": "zq_gjzq",
    "_id": 32273,
    "tagColor": "#f2384b",
    "weight": 0,
    "videoId": 0,
    "visitCount": 11,
    "tag": "西甲"
  },
  {
    "id": 32275,
    "title": "蒙奇：罗马将签下帕尔梅拉斯门将福萨托",
    "summary": "",
    "publishTime": 1530990315000,
    "isHeadline": 0,
    "headlineWeight": 1,
    "category": "zq",
    "format": 1,
    "imageList": [
      "https://qmcms.oss-cn-beijing.aliyuncs.com/sns/image/201807/16476555776.jpg"
    ],
    "lotNo": "zq_gjzq",
    "_id": 32275,
    "tagColor": "#f2384b",
    "weight": 0,
    "videoId": 0,
    "visitCount": 15,
    "tag": "意甲"
  },
  {
    "id": 32265,
    "title": "曝保利尼奥决定重返恒大 乘飞机回巴萨处理转会",
    "summary": "",
    "publishTime": 1530988020000,
    "isHeadline": 0,
    "headlineWeight": 1,
    "category": "zq",
    "format": 1,
    "imageList": [
      "https://qmcms.oss-cn-beijing.aliyuncs.com/sns/image/201807/164761e651e.jpg"
    ],
    "lotNo": "zq_zgzq",
    "_id": 32265,
    "tagColor": "#f2384b",
    "weight": 0,
    "videoId": 0,
    "visitCount": 52,
    "tag": "中超"
  },
  {
    "id": 32276,
    "title": "官方：米兰宣布与哈利洛维奇签约至2021年",
    "summary": "",
    "publishTime": 1530975600000,
    "isHeadline": 0,
    "headlineWeight": 1,
    "category": "zq",
    "format": 1,
    "imageList": [
      "https://qmcms.oss-cn-beijing.aliyuncs.com/sns/image/201807/1647579a66b.png"
    ],
    "lotNo": "zq_gjzq",
    "_id": 32276,
    "tagColor": "#f2384b",
    "weight": 0,
    "videoId": 0,
    "visitCount": 21,
    "tag": "意甲"
  },
  {
    "id": 32277,
    "title": "官方：吉罗纳与中场博尔哈-加西亚续约至2022年",
    "summary": "",
    "publishTime": 1530969420000,
    "isHeadline": 0,
    "headlineWeight": 1,
    "category": "zq",
    "format": 1,
    "imageList": [
      "https://qmcms.oss-cn-beijing.aliyuncs.com/sns/image/201807/164750bc2c1.jpg"
    ],
    "lotNo": "zq_gjzq",
    "_id": 32277,
    "tagColor": "#f2384b",
    "weight": 0,
    "videoId": 0,
    "visitCount": 5
  },
  {
    "id": 32279,
    "title": "官方：都灵和西里古续约至2022年6月",
    "summary": "",
    "publishTime": 1530963614000,
    "isHeadline": 0,
    "headlineWeight": 1,
    "category": "zq",
    "format": 1,
    "imageList": [
      "https://qmcms.oss-cn-beijing.aliyuncs.com/sns/image/201807/164749de4dd.jpg"
    ],
    "lotNo": "zq_gjzq",
    "_id": 32279,
    "tagColor": "#f2384b",
    "weight": 0,
    "videoId": 0,
    "visitCount": 6,
    "tag": "意甲"
  },
  {
    "id": 32280,
    "title": "官方：美因茨签下马德里竞技年轻中场",
    "summary": "",
    "publishTime": 1530957298000,
    "isHeadline": 0,
    "headlineWeight": 1,
    "category": "zq",
    "format": 1,
    "imageList": [
      "https://qmcms.oss-cn-beijing.aliyuncs.com/sns/image/201807/16474300804.jpg"
    ],
    "lotNo": "zq_gjzq",
    "_id": 32280,
    "tagColor": "#f2384b",
    "weight": 0,
    "videoId": 0,
    "visitCount": 14,
    "tag": "德甲 "
  },
  {
    "id": 32206,
    "title": "一语成谶？C罗1月笑称：如果1亿卖我说明他们不爱我了",
    "summary": "",
    "publishTime": 1530949900000,
    "isHeadline": 0,
    "headlineWeight": 1,
    "category": "zq",
    "format": 1,
    "imageList": [
      "https://qmcms.oss-cn-beijing.aliyuncs.com/sns/image/201807/16473c22663.jpg"
    ],
    "lotNo": "zq_gjzq",
    "_id": 32206,
    "tagColor": "#f2384b",
    "weight": 0,
    "videoId": 0,
    "visitCount": 146
  },
  {
    "id": 32207,
    "title": "英媒：阿森纳有意引进墨西哥前锋洛萨诺",
    "summary": "",
    "publishTime": 1530949720000,
    "isHeadline": 0,
    "headlineWeight": 1,
    "category": "zq",
    "format": 1,
    "imageList": [
      "https://qmcms.oss-cn-beijing.aliyuncs.com/sns/image/201807/16473c2286b.jpg"
    ],
    "lotNo": "zq_gjzq",
    "_id": 32207,
    "tagColor": "#f2384b",
    "weight": 0,
    "videoId": 0,
    "visitCount": 30
  },
  {
    "id": 32210,
    "title": "BBC：托雷拉下周加盟阿森纳，转会费可达2600万镑",
    "summary": "",
    "publishTime": 1530949321000,
    "isHeadline": 1,
    "headlineWeight": 1,
    "category": "zq",
    "format": 1,
    "imageList": [
      "https://qmcms.oss-cn-beijing.aliyuncs.com/sns/image/201807/16473c229a3.png"
    ],
    "lotNo": "zq_gjzq",
    "_id": 32210,
    "tagColor": "#12ae5b",
    "weight": 0,
    "videoId": 0,
    "visitCount": 157,
    "tag": "英超"
  },
  {
    "id": 32211,
    "title": "阿扎尔三弟前往荷兰俱乐部试训，即将离开切尔西",
    "summary": "",
    "publishTime": 1530946368000,
    "isHeadline": 0,
    "headlineWeight": 1,
    "category": "zq",
    "format": 1,
    "imageList": [
      "https://qmcms.oss-cn-beijing.aliyuncs.com/sns/image/201807/164738b3730.jpg"
    ],
    "lotNo": "zq_gjzq",
    "_id": 32211,
    "tagColor": "#f2384b",
    "weight": 0,
    "videoId": 0,
    "visitCount": 33
  },
  {
    "id": 32208,
    "title": "姆巴佩：德尚说了我在比赛中引发混乱的动作",
    "summary": "",
    "publishTime": 1530945121000,
    "isHeadline": 0,
    "headlineWeight": 1,
    "category": "zq",
    "format": 1,
    "imageList": [
      "https://qmcms.oss-cn-beijing.aliyuncs.com/sns/image/201807/164738b3a03.jpg"
    ],
    "lotNo": "zq_gjzq",
    "_id": 32208,
    "tagColor": "#f2384b",
    "weight": 0,
    "videoId": 0,
    "visitCount": 76
  },
  {
    "id": 32216,
    "title": "悉尼FC官方：中场梅热耶夫斯基离队，将前往中国效力",
    "summary": "",
    "publishTime": 1530943396000,
    "isHeadline": 0,
    "headlineWeight": 1,
    "category": "zq",
    "format": 1,
    "imageList": [
      "https://qmcms.oss-cn-beijing.aliyuncs.com/sns/image/201807/164738b3fc0.png"
    ],
    "lotNo": "zq_zgzq",
    "_id": 32216,
    "tagColor": "#f2384b",
    "weight": 0,
    "videoId": 0,
    "visitCount": 23
  },
  {
    "id": 32217,
    "title": "保利尼奥：这次出局比1-7惨败更难以接受",
    "summary": "",
    "publishTime": 1530942353000,
    "isHeadline": 1,
    "headlineWeight": 1,
    "category": "zq",
    "format": 1,
    "imageList": [
      "https://qmcms.oss-cn-beijing.aliyuncs.com/sns/image/201807/16473544934.jpg"
    ],
    "lotNo": "zq_gjzq",
    "_id": 32217,
    "tagColor": "#12ae5b",
    "weight": 0,
    "videoId": 0,
    "visitCount": 324,
    "tag": "世界杯"
  },
  {
    "id": 32209,
    "title": "吉鲁：我在以另一种方式帮助球队；或许我能在半决赛或决赛进球",
    "summary": "",
    "publishTime": 1530939106000,
    "isHeadline": 0,
    "headlineWeight": 1,
    "category": "zq",
    "format": 1,
    "imageList": [
      "https://qmcms.oss-cn-beijing.aliyuncs.com/sns/image/201807/164731d5a23.jpg"
    ],
    "lotNo": "zq_gjzq",
    "_id": 32209,
    "tagColor": "#f2384b",
    "weight": 0,
    "videoId": 0,
    "visitCount": 16
  },
  {
    "id": 32222,
    "title": "迈尔经纪人：马赛是顶级球队，暂时还没做出决定",
    "summary": "",
    "publishTime": 1530937695000,
    "isHeadline": 0,
    "headlineWeight": 1,
    "category": "zq",
    "format": 1,
    "imageList": [
      "https://qmcms.oss-cn-beijing.aliyuncs.com/sns/image/201807/164731d5d16.jpg"
    ],
    "lotNo": "zq_gjzq",
    "_id": 32222,
    "tagColor": "#f2384b",
    "weight": 0,
    "videoId": 0,
    "visitCount": 13
  },
  {
    "id": 32223,
    "title": "瓦茨克：新赛季没有冠军梦想，目标欧冠资格",
    "summary": "",
    "publishTime": 1530937299000,
    "isHeadline": 0,
    "headlineWeight": 1,
    "category": "zq",
    "format": 1,
    "imageList": [
      "https://qmcms.oss-cn-beijing.aliyuncs.com/sns/image/201807/164731d5f02.jpg"
    ],
    "lotNo": "zq_gjzq",
    "_id": 32223,
    "tagColor": "#f2384b",
    "weight": 0,
    "videoId": 0,
    "visitCount": 9
  },
  {
    "id": 32236,
    "title": "图片报：世界杯期间个别德国国脚玩游戏至深夜",
    "summary": "",
    "publishTime": 1530936346000,
    "isHeadline": 0,
    "headlineWeight": 1,
    "category": "zq",
    "format": 1,
    "imageList": [
      "https://qmcms.oss-cn-beijing.aliyuncs.com/sns/image/201807/164731d62a5.jpg"
    ],
    "lotNo": "zq_gjzq",
    "_id": 32236,
    "tagColor": "#f2384b",
    "weight": 0,
    "videoId": 0,
    "visitCount": 32
  },
  {
    "id": 32227,
    "title": "新闻报：皇马要求尤文为C罗支付1.5亿欧元",
    "summary": "",
    "publishTime": 1530936292000,
    "isHeadline": 1,
    "headlineWeight": 1,
    "category": "zq",
    "format": 1,
    "imageList": [
      "https://qmcms.oss-cn-beijing.aliyuncs.com/sns/image/201807/164731d63a6.jpg"
    ],
    "lotNo": "zq_gjzq",
    "_id": 32227,
    "tagColor": "#12ae5b",
    "weight": 0,
    "videoId": 0,
    "visitCount": 122,
    "tag": "西甲"
  },
  {
    "id": 32229,
    "title": "法夫尔：期待和罗伊斯合作，要注重于反击打法",
    "summary": "",
    "publishTime": 1530935924000,
    "isHeadline": 0,
    "headlineWeight": 1,
    "category": "zq",
    "format": 1,
    "imageList": [
      "https://qmcms.oss-cn-beijing.aliyuncs.com/sns/image/201807/16472e66b8f.jpg"
    ],
    "lotNo": "zq_gjzq",
    "_id": 32229,
    "tagColor": "#f2384b",
    "weight": 0,
    "videoId": 0,
    "visitCount": 12
  },
  {
    "id": 32195,
    "title": "卡瓦尼：非常伤心，但感谢上帝让我们有这样的经历",
    "summary": "",
    "publishTime": 1530928230000,
    "isHeadline": 0,
    "headlineWeight": 1,
    "category": "zq",
    "format": 1,
    "imageList": [
      "https://qmcms.oss-cn-beijing.aliyuncs.com/sns/image/201807/164727890bd.jpg"
    ],
    "lotNo": "zq_gjzq",
    "_id": 32195,
    "tagColor": "#f2384b",
    "weight": 0,
    "videoId": 0,
    "visitCount": 100
  },
  {
    "id": 32196,
    "title": "回声报：杰拉德租借利物浦球员时有优先权",
    "summary": "",
    "publishTime": 1530925714000,
    "isHeadline": 0,
    "headlineWeight": 1,
    "category": "zq",
    "format": 1,
    "imageList": [
      "https://qmcms.oss-cn-beijing.aliyuncs.com/sns/image/201807/164727892f5.jpg"
    ],
    "lotNo": "zq_gjzq",
    "_id": 32196,
    "tagColor": "#f2384b",
    "weight": 0,
    "videoId": 0,
    "visitCount": 51,
    "tag": "英超"
  },
  {
    "id": 32181,
    "title": "官宣：大博阿滕重返意甲 正式加盟萨索洛俱乐部",
    "summary": "",
    "publishTime": 1530924556000,
    "isHeadline": 0,
    "headlineWeight": 1,
    "category": "zq",
    "format": 1,
    "imageList": [
      "https://qmcms.oss-cn-beijing.aliyuncs.com/sns/image/201807/1647241ca56.png"
    ],
    "lotNo": "zq_gjzq",
    "_id": 32181,
    "tagColor": "#f2384b",
    "weight": 0,
    "videoId": 0,
    "visitCount": 31
  },
  {
    "id": 32182,
    "title": "多特主管佐尔克称赞新帅法夫尔：他让每名球员变得更好",
    "summary": "",
    "publishTime": 1530923102000,
    "isHeadline": 0,
    "headlineWeight": 1,
    "category": "zq",
    "format": 1,
    "imageList": [
      "https://qmcms.oss-cn-beijing.aliyuncs.com/sns/image/201807/1647241a267.jpg"
    ],
    "lotNo": "zq_gjzq",
    "_id": 32182,
    "tagColor": "#f2384b",
    "weight": 0,
    "videoId": 0,
    "visitCount": 10
  },
  {
    "id": 32183,
    "title": "保利尼奥：的确收到中超报价，仍需与经纪人商讨",
    "summary": "",
    "publishTime": 1530917602000,
    "isHeadline": 0,
    "headlineWeight": 1,
    "category": "zq",
    "format": 1,
    "imageList": [
      "https://qmcms.oss-cn-beijing.aliyuncs.com/sns/image/201807/16471d3c226.png"
    ],
    "lotNo": "zq_gjzq",
    "_id": 32183,
    "tagColor": "#f2384b",
    "weight": 0,
    "videoId": 0,
    "visitCount": 54,
    "tag": "西甲"
  },
  {
    "id": 32184,
    "title": "拒绝中超报价，巴洛特利将和马赛签约两年",
    "summary": "",
    "publishTime": 1530916696000,
    "isHeadline": 0,
    "headlineWeight": 1,
    "category": "zq",
    "format": 1,
    "imageList": [
      "https://qmcms.oss-cn-beijing.aliyuncs.com/sns/image/201807/16471d3c76c.jpg"
    ],
    "lotNo": "zq_gjzq",
    "_id": 32184,
    "tagColor": "#f2384b",
    "weight": 0,
    "videoId": 0,
    "visitCount": 36,
    "tag": "法甲"
  },
  {
    "id": 32185,
    "title": "纳因戈兰遭遇交通事故，但所幸没有受伤",
    "summary": "",
    "publishTime": 1530916380000,
    "isHeadline": 1,
    "headlineWeight": 1,
    "category": "zq",
    "format": 1,
    "imageList": [
      "https://qmcms.oss-cn-beijing.aliyuncs.com/sns/image/201807/16471d3c9fb.jpg"
    ],
    "lotNo": "zq_gjzq",
    "_id": 32185,
    "tagColor": "#f2384b",
    "weight": 0,
    "videoId": 0,
    "visitCount": 75,
    "tag": "意甲"
  },
  {
    "id": 32198,
    "title": "U20女足四国赛：谢绮文、智杰建功，中国2-0泰国",
    "summary": "",
    "publishTime": 1530896844000,
    "isHeadline": 0,
    "headlineWeight": 1,
    "category": "zq",
    "format": 1,
    "imageList": [
      "https://qmcms.oss-cn-beijing.aliyuncs.com/sns/image/201807/16470c1a3dd.jpg"
    ],
    "lotNo": "zq_zgzq",
    "_id": 32198,
    "tagColor": "#f2384b",
    "weight": 0,
    "videoId": 0,
    "visitCount": 17,
    "tag": "中国足球 "
  },
  {
    "id": 32189,
    "title": "官方：巴黎圣日耳曼签下意大利门将布冯",
    "summary": "",
    "publishTime": 1530896466000,
    "isHeadline": 1,
    "headlineWeight": 1,
    "category": "zq",
    "format": 1,
    "imageList": [
      "https://qmcms.oss-cn-beijing.aliyuncs.com/sns/image/201807/16470c19d42.png"
    ],
    "lotNo": "zq_gjzq",
    "_id": 32189,
    "tagColor": "#f2384b",
    "weight": 0,
    "videoId": 0,
    "visitCount": 54,
    "tag": "法甲"
  },
  {
    "id": 32190,
    "title": "官方：桑普多利亚签下乌迪内斯中场扬克托",
    "summary": "",
    "publishTime": 1530893460000,
    "isHeadline": 0,
    "headlineWeight": 1,
    "category": "zq",
    "format": 1,
    "imageList": [
      "https://qmcms.oss-cn-beijing.aliyuncs.com/sns/image/201807/164708a3f4f.jpg"
    ],
    "lotNo": "zq_gjzq",
    "_id": 32190,
    "tagColor": "#f2384b",
    "weight": 0,
    "videoId": 0,
    "visitCount": 7,
    "tag": "意甲"
  },
  {
    "id": 32197,
    "title": "官方：前江苏外援埃斯库德罗加盟韩国球队蔚山现代",
    "summary": "",
    "publishTime": 1530891440000,
    "isHeadline": 0,
    "headlineWeight": 1,
    "category": "zq",
    "format": 1,
    "imageList": [
      "https://qmcms.oss-cn-beijing.aliyuncs.com/sns/image/201807/164705347f1.jpg"
    ],
    "lotNo": "zq_zgzq",
    "_id": 32197,
    "tagColor": "#f2384b",
    "weight": 0,
    "videoId": 0,
    "visitCount": 6
  },
  {
    "id": 32192,
    "title": "巴萨喉舌:佛爷不想为C罗办告别仪式 也不会有纪念",
    "summary": "",
    "publishTime": 1530889665000,
    "isHeadline": 0,
    "headlineWeight": 1,
    "category": "zq",
    "format": 1,
    "imageList": [
      "https://qmcms.oss-cn-beijing.aliyuncs.com/sns/image/201807/16470536dbb.jpg"
    ],
    "lotNo": "zq_gjzq",
    "_id": 32192,
    "tagColor": "#f2384b",
    "weight": 0,
    "videoId": 0,
    "visitCount": 44,
    "tag": "西甲"
  },
  {
    "id": 32096,
    "title": "里皮：7月底将返回中国，70岁的我精力在下降",
    "summary": "",
    "publishTime": 1530886978000,
    "isHeadline": 0,
    "headlineWeight": 1,
    "category": "zq",
    "format": 1,
    "imageList": [
      "https://qmcms.oss-cn-beijing.aliyuncs.com/sns/image/201807/1646af5fa78.jpg"
    ],
    "lotNo": "zq_zgzq",
    "_id": 32096,
    "tagColor": "#f2384b",
    "weight": 0,
    "videoId": 0,
    "visitCount": 109,
    "tag": "中国足球 "
  },
  {
    "id": 32193,
    "title": "官方：阿拉维斯签下拉斯帕尔马斯后卫纳瓦罗",
    "summary": "",
    "publishTime": 1530882780000,
    "isHeadline": 0,
    "headlineWeight": 1,
    "category": "zq",
    "format": 1,
    "imageList": [
      "https://qmcms.oss-cn-beijing.aliyuncs.com/sns/image/201807/1646fe5669a.png"
    ],
    "lotNo": "zq_gjzq",
    "_id": 32193,
    "tagColor": "#f2384b",
    "weight": 0,
    "videoId": 0,
    "visitCount": 11,
    "tag": "西甲"
  },
  {
    "id": 32194,
    "title": "药厂有意卡利尼奇，但后者更愿加盟马竞",
    "summary": "",
    "publishTime": 1530878606000,
    "isHeadline": 0,
    "headlineWeight": 1,
    "category": "zq",
    "format": 1,
    "imageList": [
      "https://qmcms.oss-cn-beijing.aliyuncs.com/sns/image/201807/1646fae9016.jpg"
    ],
    "lotNo": "zq_gjzq",
    "_id": 32194,
    "tagColor": "#f2384b",
    "weight": 0,
    "videoId": 0,
    "visitCount": 9,
    "tag": "意甲"
  },
  {
    "id": 32138,
    "title": "佩莱格里尼：想留在罗马，C罗来尤文对意甲是好事",
    "summary": "",
    "publishTime": 1530877560000,
    "isHeadline": 0,
    "headlineWeight": 1,
    "category": "zq",
    "format": 1,
    "imageList": [
      "https://qmcms.oss-cn-beijing.aliyuncs.com/sns/image/201807/1646f778324.jpg"
    ],
    "lotNo": "zq_gjzq",
    "_id": 32138,
    "tagColor": "#f2384b",
    "weight": 0,
    "videoId": 0,
    "visitCount": 51
  },
  {
    "id": 32139,
    "title": "迪马济奥：马竞与热尔松马丁斯达成个人协议",
    "summary": "",
    "publishTime": 1530877389000,
    "isHeadline": 0,
    "headlineWeight": 1,
    "category": "zq",
    "format": 1,
    "imageList": [
      "https://qmcms.oss-cn-beijing.aliyuncs.com/sns/image/201807/1646f778648.jpg"
    ],
    "lotNo": "zq_gjzq",
    "_id": 32139,
    "tagColor": "#f2384b",
    "weight": 0,
    "videoId": 0,
    "visitCount": 18
  },
  {
    "id": 32140,
    "title": "法媒：拉比奥暂未与巴黎续约，他要求年薪与维拉蒂持平",
    "summary": "",
    "publishTime": 1530874993000,
    "isHeadline": 0,
    "headlineWeight": 1,
    "category": "zq",
    "format": 1,
    "imageList": [
      "https://qmcms.oss-cn-beijing.aliyuncs.com/sns/image/201807/1646f778786.jpg"
    ],
    "lotNo": "zq_gjzq",
    "_id": 32140,
    "tagColor": "#f2384b",
    "weight": 0,
    "videoId": 0,
    "visitCount": 24
  },
  {
    "id": 32142,
    "title": "西班牙媒体：保利尼奥非常接近于重返广州恒大",
    "summary": "",
    "publishTime": 1530873785000,
    "isHeadline": 1,
    "headlineWeight": 1,
    "category": "zq",
    "format": 1,
    "imageList": [
      "https://qmcms.oss-cn-beijing.aliyuncs.com/sns/image/201807/1646f409e94.jpg"
    ],
    "lotNo": "zq_zgzq",
    "_id": 32142,
    "tagColor": "#12ae5b",
    "weight": 0,
    "videoId": 0,
    "visitCount": 150,
    "tag": "中超"
  },
  {
    "id": 32141,
    "title": "官方：切尔西17岁青年后卫潘佐转会摩纳哥",
    "summary": "",
    "publishTime": 1530871239000,
    "isHeadline": 0,
    "headlineWeight": 1,
    "category": "zq",
    "format": 1,
    "imageList": [
      "https://qmcms.oss-cn-beijing.aliyuncs.com/sns/image/201807/1646f409c15.png"
    ],
    "lotNo": "zq_gjzq",
    "_id": 32141,
    "tagColor": "#f2384b",
    "weight": 0,
    "videoId": 0,
    "visitCount": 16
  },
  {
    "id": 32145,
    "title": "米体：布冯下周一将正式加盟巴黎圣日耳曼",
    "summary": "",
    "publishTime": 1530864880000,
    "isHeadline": 0,
    "headlineWeight": 1,
    "category": "zq",
    "format": 1,
    "imageList": [
      "https://qmcms.oss-cn-beijing.aliyuncs.com/sns/image/201807/1646ed2bb11.jpg"
    ],
    "lotNo": "zq_gjzq",
    "_id": 32145,
    "tagColor": "#f2384b",
    "weight": 0,
    "videoId": 0,
    "visitCount": 24
  },
  {
    "id": 32147,
    "title": "米体：皇马要求尤文为C罗支付1.2亿-1.3亿欧元",
    "summary": "",
    "publishTime": 1530864313000,
    "isHeadline": 1,
    "headlineWeight": 1,
    "category": "zq",
    "format": 1,
    "imageList": [
      "https://qmcms.oss-cn-beijing.aliyuncs.com/sns/image/201807/1646ed2bbb0.jpg"
    ],
    "lotNo": "zq_gjzq",
    "_id": 32147,
    "tagColor": "#12ae5b",
    "weight": 0,
    "videoId": 0,
    "visitCount": 134,
    "tag": "西甲"
  },
  {
    "id": 32133,
    "title": "镜报：英格兰国门皮克福德与梅根已秘密订婚",
    "summary": "",
    "publishTime": 1530859952000,
    "isHeadline": 0,
    "headlineWeight": 1,
    "category": "zq",
    "format": 1,
    "imageList": [
      "https://qmcms.oss-cn-beijing.aliyuncs.com/sns/image/201807/1646e64db13.jpg"
    ],
    "lotNo": "zq_gjzq",
    "_id": 32133,
    "tagColor": "#f2384b",
    "weight": 0,
    "videoId": 0,
    "visitCount": 66
  },
  {
    "id": 32132,
    "title": "孙雯、罗纳尔多领衔国际足联年度最佳奖项评审团",
    "summary": "",
    "publishTime": 1530859895000,
    "isHeadline": 1,
    "headlineWeight": 1,
    "category": "zq",
    "format": 1,
    "imageList": [
      "https://qmcms.oss-cn-beijing.aliyuncs.com/sns/image/201807/1646e64e05a.jpg"
    ],
    "lotNo": "zq_zgzq",
    "_id": 32132,
    "tagColor": "#12ae5b",
    "weight": 0,
    "videoId": 0,
    "visitCount": 445,
    "tag": "世界杯"
  },
  {
    "id": 32125,
    "title": "马卡报：皮克的游戏公司在亏损200万欧元后倒闭",
    "summary": "",
    "publishTime": 1530856732000,
    "isHeadline": 0,
    "headlineWeight": 1,
    "category": "zq",
    "format": 1,
    "imageList": [
      "https://qmcms.oss-cn-beijing.aliyuncs.com/sns/image/201807/1646e2debff.jpg"
    ],
    "lotNo": "zq_gjzq",
    "_id": 32125,
    "tagColor": "#f2384b",
    "weight": 0,
    "videoId": 0,
    "visitCount": 38
  },
  {
    "id": 32120,
    "title": "官方：富勒姆与冲超功勋队长凯尔内续约5年",
    "summary": "",
    "publishTime": 1530855594000,
    "isHeadline": 1,
    "headlineWeight": 1,
    "category": "zq",
    "format": 1,
    "imageList": [
      "https://qmcms.oss-cn-beijing.aliyuncs.com/sns/image/201807/1646e2dedb5.jpg"
    ],
    "lotNo": "zq_gjzq",
    "_id": 32120,
    "tagColor": "#12ae5b",
    "weight": 0,
    "videoId": 0,
    "visitCount": 44,
    "tag": "英超"
  },
  {
    "id": 32114,
    "title": "斯通斯：哥伦比亚是我碰到最脏的球队",
    "summary": "",
    "publishTime": 1530850234000,
    "isHeadline": 0,
    "headlineWeight": 1,
    "category": "zq",
    "format": 1,
    "imageList": [
      "https://qmcms.oss-cn-beijing.aliyuncs.com/sns/image/201807/1646df6fcb9.png"
    ],
    "lotNo": "zq_gjzq",
    "_id": 32114,
    "tagColor": "#f2384b",
    "weight": 0,
    "videoId": 0,
    "visitCount": 50
  },
  {
    "id": 32108,
    "title": "虽被淘汰出局，哥伦比亚仍在国内受到了英雄般的待遇",
    "summary": "",
    "publishTime": 1530849211000,
    "isHeadline": 1,
    "headlineWeight": 1,
    "category": "zq",
    "format": 1,
    "imageList": [
      "https://qmcms.oss-cn-beijing.aliyuncs.com/sns/image/201807/1646dc0101e.jpg"
    ],
    "lotNo": "zq_gjzq",
    "_id": 32108,
    "tagColor": "#12ae5b",
    "weight": 0,
    "videoId": 0,
    "visitCount": 300,
    "tag": "世界杯"
  },
  {
    "id": 32111,
    "title": "通情达理，主教练批准马奎尔弟弟去俄罗斯看世界杯",
    "summary": "",
    "publishTime": 1530847345000,
    "isHeadline": 0,
    "headlineWeight": 1,
    "category": "zq",
    "format": 1,
    "imageList": [
      "https://qmcms.oss-cn-beijing.aliyuncs.com/sns/image/201807/1646dc01354.png"
    ],
    "lotNo": "zq_gjzq",
    "_id": 32111,
    "tagColor": "#f2384b",
    "weight": 0,
    "videoId": 0,
    "visitCount": 37
  },
  {
    "id": 32113,
    "title": "法媒：布冯今天将抵达巴黎进行体检，将是巴黎今夏首笔引援",
    "summary": "",
    "publishTime": 1530847231000,
    "isHeadline": 1,
    "headlineWeight": 1,
    "category": "zq",
    "format": 1,
    "imageList": [
      "https://qmcms.oss-cn-beijing.aliyuncs.com/sns/image/201807/1646dc014b6.jpg"
    ],
    "lotNo": "zq_gjzq",
    "_id": 32113,
    "tagColor": "#12ae5b",
    "weight": 0,
    "videoId": 0,
    "visitCount": 39,
    "tag": "法甲"
  },
  {
    "id": 32102,
    "title": "苏亚雷斯和队友玩FIFA，选利物浦8-2击败巴萨",
    "summary": "",
    "publishTime": 1530844710000,
    "isHeadline": 0,
    "headlineWeight": 1,
    "category": "zq",
    "format": 1,
    "imageList": [
      "https://qmcms.oss-cn-beijing.aliyuncs.com/sns/image/201807/1646d892705.png"
    ],
    "lotNo": "zq_gjzq",
    "_id": 32102,
    "tagColor": "#f2384b",
    "weight": 0,
    "videoId": 0,
    "visitCount": 46
  },
  {
    "id": 32070,
    "title": "卫报：威尔希尔周四已体检，将和西汉姆联签约三年",
    "summary": "",
    "publishTime": 1530841801000,
    "isHeadline": 0,
    "headlineWeight": 1,
    "category": "zq",
    "format": 1,
    "imageList": [
      "https://qmcms.oss-cn-beijing.aliyuncs.com/sns/image/201807/1646d523249.jpg"
    ],
    "lotNo": "zq_gjzq",
    "_id": 32070,
    "tagColor": "#f2384b",
    "weight": 0,
    "videoId": 0,
    "visitCount": 21
  },
  {
    "id": 32071,
    "title": "意媒：利物浦已经接触尤文图斯前锋迪巴拉",
    "summary": "",
    "publishTime": 1530839953000,
    "isHeadline": 1,
    "headlineWeight": 1,
    "category": "zq",
    "format": 1,
    "imageList": [
      "https://qmcms.oss-cn-beijing.aliyuncs.com/sns/image/201807/1646d523681.png"
    ],
    "lotNo": "zq_gjzq",
    "_id": 32071,
    "tagColor": "#f2384b",
    "weight": 0,
    "videoId": 0,
    "visitCount": 30,
    "tag": "意甲"
  },
  {
    "id": 32074,
    "title": "马图伊迪：为停赛感到难过，会站在队友身后帮助他们",
    "summary": "",
    "publishTime": 1530838342000,
    "isHeadline": 0,
    "headlineWeight": 1,
    "category": "zq",
    "format": 1,
    "imageList": [
      "https://qmcms.oss-cn-beijing.aliyuncs.com/sns/image/201807/1646d1b453b.jpg"
    ],
    "lotNo": "zq_gjzq",
    "_id": 32074,
    "tagColor": "#f2384b",
    "weight": 0,
    "videoId": 0,
    "visitCount": 22
  },
  {
    "id": 32072,
    "title": "克洛普：凯塔与法比尼奥周六上演红军处子秀",
    "summary": "",
    "publishTime": 1530838336000,
    "isHeadline": 1,
    "headlineWeight": 1,
    "category": "zq",
    "format": 1,
    "imageList": [
      "https://qmcms.oss-cn-beijing.aliyuncs.com/sns/image/201807/1646d1b46b3.jpg"
    ],
    "lotNo": "zq_gjzq",
    "_id": 32072,
    "tagColor": "#f2384b",
    "weight": 0,
    "videoId": 0,
    "visitCount": 35,
    "tag": "英超"
  },
  {
    "id": 32075,
    "title": "药厂主帅期待再签两名新援：一个左后卫和一个中锋",
    "summary": "",
    "publishTime": 1530833474000,
    "isHeadline": 0,
    "headlineWeight": 1,
    "category": "zq",
    "format": 1,
    "imageList": [
      "https://qmcms.oss-cn-beijing.aliyuncs.com/sns/image/201807/1646ce4585c.jpg"
    ],
    "lotNo": "zq_gjzq",
    "_id": 32075,
    "tagColor": "#f2384b",
    "weight": 0,
    "videoId": 0,
    "visitCount": 11
  },
  {
    "id": 32076,
    "title": "官方：英超布莱顿签下莱比锡边卫贝尔纳多",
    "summary": "",
    "publishTime": 1530832918000,
    "isHeadline": 0,
    "headlineWeight": 1,
    "category": "zq",
    "format": 1,
    "imageList": [
      "https://qmcms.oss-cn-beijing.aliyuncs.com/sns/image/201807/1646ce459d9.jpg"
    ],
    "lotNo": "zq_gjzq",
    "_id": 32076,
    "tagColor": "#f2384b",
    "weight": 0,
    "videoId": 0,
    "visitCount": 10
  }
]